{
  "user": [],
  "users": [
    {
      "id": "sdfsafsaf",
      "name": "Tong Giang"
    },
    {
      "name": "Lam Xung",
      "id": "ZHaRGTSpx"
    },
    {
      "name": "Lo Tri Tham",
      "id": "Oe7kfQe6J"
    },
    {
      "name": "Võ Tòng",
      "id": "Y9SraYdft"
    },
    {
      "name": "Admin",
      "id": "18TDVGGCd",
      "email": "admin@gmail.com",
      "password": "123456"
    },
    {
      "name": "Lam Xung",
      "id": "k3alX2LNy"
    },
    {
      "name": "hihihi",
      "id": "eE0TRbZU0"
    },
    {
      "name": "Lam Xung",
      "phone": "123123123",
      "id": "a0Icl8c3C"
    },
    {
      "name": "Lam Xung",
      "phone": "12312",
      "id": "xsnDPz_oW"
    },
    {
      "name": "",
      "phone": "",
      "id": "jvWrpzue-"
    },
    {
      "name": "",
      "phone": "",
      "id": "DDeB1FEAy"
    },
    {
      "name": "",
      "phone": "",
      "id": "TpPV91-Sd"
    }
  ]
}